README.md
setup.py
gym_tool_use/__init__.py
gym_tool_use/play.py
gym_tool_use/transfer_examples.py
gym_tool_use/transfers.py
gym_tool_use/trap_tube_env.py
gym_tool_use/trap_tube_env_test.py
gym_tool_use.egg-info/PKG-INFO
gym_tool_use.egg-info/SOURCES.txt
gym_tool_use.egg-info/dependency_links.txt
gym_tool_use.egg-info/requires.txt
gym_tool_use.egg-info/top_level.txt