Metadata-Version: 2.1
Name: gym-tool-use
Version: 1.0.0
Summary: Gym tool use environments.
Home-page: https://github.com/fomorians/gym_tool_use
Author: Fomoro AI
Author-email: team@fomoro.com
License: Apache 2.0
Download-URL: https://github.com/fomorians/gym_tool_use/archive/v1.0.0.tar.gz
Keywords: gym,pycolab,reinforcement-learning,tool-use
Platform: UNKNOWN
Classifier: Intended Audience :: Science/Research
Classifier: Intended Audience :: Developers
Classifier: License :: OSI Approved :: Apache Software License
Classifier: Programming Language :: Python :: 2
Classifier: Programming Language :: Python :: 2.7
Classifier: Programming Language :: Python :: 3
Classifier: Programming Language :: Python :: 3.5
Classifier: Programming Language :: Python :: 3.6
Classifier: Operating System :: OS Independent
Classifier: Development Status :: 3 - Alpha
